django_events_rest_framework-0.1.dist-info/METADATA
django_events_rest_framework-0.1.dist-info/RECORD
django_events_rest_framework-0.1.dist-info/WHEEL
django_events_rest_framework-0.1.dist-info/top_level.txt
events/__init__.py
events/admin.py
events/apps.py
events/models.py
events/serializers.py
events/tests.py
events/urls.py
events/views.py
events/week.py
events/migrations/0001_initial.py
events/migrations/0002_occurrences.py
events/migrations/0003_auto_20180618_0556.py
events/migrations/0004_auto_20180618_0602.py
events/migrations/0005_auto_20180618_0742.py
events/migrations/__init__.py
