Metadata-Version: 2.1
Name: django-events-rest-framework
Version: 0.1
Summary: A package to easily schedule events with full calendar in Django Rest Framework.
Home-page: https://aswinzz.github.io/
Author: aswinzz
Author-email: aswinvb.aswin6@gmail.com
License: MIT License
Platform: UNKNOWN
Classifier: Environment :: Web Environment
Classifier: Framework :: Django
Classifier: Framework :: Django :: 1.11
Classifier: Intended Audience :: Developers
Classifier: License :: OSI Approved :: MIT License
Classifier: Operating System :: OS Independent
Classifier: Programming Language :: Python
Classifier: Programming Language :: Python :: 3.5
Classifier: Programming Language :: Python :: 3.6
Classifier: Topic :: Internet :: WWW/HTTP
Classifier: Topic :: Internet :: WWW/HTTP :: Dynamic Content
